{
  "gitSyncId": "66fb995faf2b8e5a2a63f337_2891b151-c23f-4b07-9ecf-e1d14564fe0c",
  "id": "Registeration_getComplaintsTitles",
  "pluginId": "mysql-plugin",
  "pluginType": "DB",
  "unpublishedAction": {
    "actionConfiguration": {
      "body": "SELECT * FROM complaints_title where name='{{this.params.title_name}}';",
      "encodeParamsToggle": true,
      "paginationType": "NONE",
      "pluginSpecifiedTemplates": [
        {
          "value": true
        }
      ],
      "timeoutInMillisecond": 100000
    },
    "confirmBeforeExecute": false,
    "datasource": {
      "id": "ResearchDB",
      "isAutoGenerated": false,
      "name": "ResearchDB",
      "pluginId": "mysql-plugin"
    },
    "dynamicBindingPathList": [
      {
        "key": "body"
      }
    ],
    "executeOnLoad": false,
    "name": "getComplaintsTitles",
    "pageId": "Registeration",
    "userSetOnLoad": false
  }
}