{
  "gitSyncId": "66fb995faf2b8e5a2a63f337_feab1831-f1dc-4d21-ac24-8c69240f983e",
  "id": "Registeration_signOut.signOut",
  "pluginId": "js-plugin",
  "pluginType": "JS",
  "unpublishedAction": {
    "actionConfiguration": {
      "encodeParamsToggle": true,
      "jsArguments": [],
      "paginationType": "NONE",
      "timeoutInMillisecond": 10000
    },
    "collectionId": "Registeration_signOut",
    "confirmBeforeExecute": false,
    "datasource": {
      "isAutoGenerated": false,
      "name": "UNUSED_DATASOURCE",
      "pluginId": "js-plugin"
    },
    "dynamicBindingPathList": [
      {
        "key": "body"
      }
    ],
    "executeOnLoad": false,
    "fullyQualifiedName": "signOut.signOut",
    "name": "signOut",
    "pageId": "Registeration",
    "userSetOnLoad": false
  }
}