{
  "gitSyncId": "66f3bdc1af2b8e5a2a63d6e6_b0ef0452-024b-4c94-b1cf-675941a37b14",
  "id": "Login_signInRightHolder",
  "pluginId": "mysql-plugin",
  "pluginType": "DB",
  "unpublishedAction": {
    "actionConfiguration": {
      "body": "{{login.signInQuery}}",
      "encodeParamsToggle": true,
      "paginationType": "NONE",
      "pluginSpecifiedTemplates": [
        {
          "value": false
        }
      ],
      "timeoutInMillisecond": 100000
    },
    "confirmBeforeExecute": false,
    "datasource": {
      "id": "ResearchDB",
      "isAutoGenerated": false,
      "name": "ResearchDB",
      "pluginId": "mysql-plugin"
    },
    "dynamicBindingPathList": [
      {
        "key": "body"
      }
    ],
    "executeOnLoad": false,
    "name": "signInRightHolder",
    "pageId": "Login",
    "userSetOnLoad": false
  }
}